wdiffhtml/__init__.py
wdiffhtml/__main__.py
wdiffhtml/cli.py
wdiffhtml/exceptions.py
wdiffhtml/settings.py
wdiffhtml/utils.py
wdiffhtml/data/main.js
wdiffhtml/data/secondary.js
wdiffhtml/data/styles.css
wdiffhtml/data/template.jinja
wdiffhtml-0.6.1.dist-info/DESCRIPTION.rst
wdiffhtml-0.6.1.dist-info/METADATA
wdiffhtml-0.6.1.dist-info/RECORD
wdiffhtml-0.6.1.dist-info/WHEEL
wdiffhtml-0.6.1.dist-info/entry_points.txt
wdiffhtml-0.6.1.dist-info/metadata.json
wdiffhtml-0.6.1.dist-info/top_level.txt
