Metadata-Version: 2.0
Name: wdiffhtml
Version: 0.6.1
Summary: Uses `wdiff`_ to generate a word based *diff* from plain text files.
Home-page: https://github.com/brutus/wdiffhtml
Author: Brutus [DMC]
Author-email: brutus.dmc@googlemail.com
License: GNU GPLv3
Platform: UNKNOWN
Classifier: License :: OSI Approved :: GNU General Public License v3 or later (GPLv3+)
Classifier: Programming Language :: Python :: 2
Classifier: Programming Language :: Python :: 3
Classifier: Development Status :: 4 - Beta
Classifier: Environment :: Console
Classifier: Topic :: Text Processing
Classifier: Topic :: Utilities
Requires-Dist: appdirs
Requires-Dist: jinja2
Requires-Dist: setuptools
Provides-Extra: dev
Requires-Dist: bumpversion; extra == 'dev'
Requires-Dist: invoke; extra == 'dev'
Provides-Extra: test
Requires-Dist: testfixtures; extra == 'test'
Requires-Dist: tox; extra == 'test'
